setup.py
Viditkj_guassian1.egg-info/PKG-INFO
Viditkj_guassian1.egg-info/SOURCES.txt
Viditkj_guassian1.egg-info/dependency_links.txt
Viditkj_guassian1.egg-info/not-zip-safe
Viditkj_guassian1.egg-info/top_level.txt
distributions/__init__.py