Metadata-Version: 1.0
Name: Viditkj-guassian1
Version: 0.3
Summary: Gaussian distributions
Home-page: UNKNOWN
Author: Vidit Kumar Jain
Author-email: viditkj25@gmail.com
License: UNKNOWN
Platform: UNKNOWN
